querycolumns/__init__.py
querycolumns-0.1.0.dist-info/LICENSE
querycolumns-0.1.0.dist-info/METADATA
querycolumns-0.1.0.dist-info/WHEEL
querycolumns-0.1.0.dist-info/top_level.txt
querycolumns-0.1.0.dist-info/RECORD
