Metadata-Version: 2.1
Name: querycolumns
Version: 0.1.0
Summary: Pandas utility for handling very wide DataFrames
Home-page: https://github.com/yaniv-aknin/querycolumns
Author: Yaniv Aknin
Author-email: yaniv@aknin.name
License: MIT
Platform: UNKNOWN
Requires-Dist: pandas
Provides-Extra: dev
Requires-Dist: pytest ; extra == 'dev'
